fundamint/__init__.py
fundamint/cli.py
fundamint/api/__init__.py
fundamint/api/server.py
fundamint/models/__init__.py
fundamint/models/analyzer.py
fundamint/models/summarizer.py
fundamint/models/trainer.py
fundamint/news/__init__.py
fundamint/news/collector.py
fundamint/news/processor.py
fundamint/utils/__init__.py
fundamint/utils/report_generator.py
fundamint/utils/stock_data.py
fundamint-0.1.1.dist-info/LICENSE
fundamint-0.1.1.dist-info/METADATA
fundamint-0.1.1.dist-info/WHEEL
fundamint-0.1.1.dist-info/entry_points.txt
fundamint-0.1.1.dist-info/top_level.txt
fundamint-0.1.1.dist-info/RECORD
